pynat.py
pynat-0.6.0.dist-info/DESCRIPTION.rst
pynat-0.6.0.dist-info/METADATA
pynat-0.6.0.dist-info/RECORD
pynat-0.6.0.dist-info/WHEEL
pynat-0.6.0.dist-info/entry_points.txt
pynat-0.6.0.dist-info/metadata.json
pynat-0.6.0.dist-info/top_level.txt
