Metadata-Version: 2.0
Name: pynat
Version: 0.6.0
Summary: Discover external IP addresses and NAT topologies using STUN.
Home-page: https://github.com/arantonitis/pynat
Author: Ariel Antonitis
Author-email: arant@mit.edu
License: MIT
Platform: UNKNOWN
Classifier: License :: OSI Approved :: MIT License
Classifier: Development Status :: 4 - Beta
Classifier: Intended Audience :: Developers
Classifier: Topic :: System :: Networking :: Firewalls
Classifier: Programming Language :: Python :: 2.7
Classifier: Programming Language :: Python :: 3.2
Classifier: Programming Language :: Python :: 3.3
Classifier: Programming Language :: Python :: 3.4
Classifier: Programming Language :: Python :: 3.5
Classifier: Programming Language :: Python :: 3.6
Requires-Python: >=2.7
